django_1.6_fine_uploader-0.2.0.1.dist-info/METADATA
django_1.6_fine_uploader-0.2.0.1.dist-info/RECORD
django_1.6_fine_uploader-0.2.0.1.dist-info/WHEEL
django_1.6_fine_uploader-0.2.0.1.dist-info/top_level.txt
django_fine_uploader/__init__.py
django_fine_uploader/fineuploader.py
django_fine_uploader/forms.py
django_fine_uploader/models.py
django_fine_uploader/settings.py
django_fine_uploader/urls.py
django_fine_uploader/utils.py
django_fine_uploader/views.py
django_fine_uploader/widgets.py
django_fine_uploader/static/django_fine_uploader/continue.gif
django_fine_uploader/static/django_fine_uploader/dnd.js
django_fine_uploader/static/django_fine_uploader/dnd.min.js
django_fine_uploader/static/django_fine_uploader/edit.gif
django_fine_uploader/static/django_fine_uploader/fine-uploader-gallery.css
django_fine_uploader/static/django_fine_uploader/fine-uploader-gallery.min.css
django_fine_uploader/static/django_fine_uploader/fine-uploader-new.css
django_fine_uploader/static/django_fine_uploader/fine-uploader-new.min.css
django_fine_uploader/static/django_fine_uploader/fine-uploader.core.js
django_fine_uploader/static/django_fine_uploader/fine-uploader.core.min.js
django_fine_uploader/static/django_fine_uploader/fine-uploader.css
django_fine_uploader/static/django_fine_uploader/fine-uploader.js
django_fine_uploader/static/django_fine_uploader/fine-uploader.min.css
django_fine_uploader/static/django_fine_uploader/fine-uploader.min.js
django_fine_uploader/static/django_fine_uploader/jquery.fine-uploader.js
django_fine_uploader/static/django_fine_uploader/jquery.fine-uploader.min.js
django_fine_uploader/static/django_fine_uploader/loading.gif
django_fine_uploader/static/django_fine_uploader/pause.gif
django_fine_uploader/static/django_fine_uploader/processing.gif
django_fine_uploader/static/django_fine_uploader/retry.gif
django_fine_uploader/static/django_fine_uploader/trash.gif
django_fine_uploader/static/django_fine_uploader/placeholders/not_available-generic.png
django_fine_uploader/static/django_fine_uploader/placeholders/waiting-generic.png
django_fine_uploader/static/django_fine_uploader/templates/default.html
