Metadata-Version: 2.1
Name: django-1.6-fine-uploader
Version: 0.2.0.1
Summary: Simple, Chunked and Concurrent uploads with Django + Fine Uploader
Home-page: https://github.com/cic79/django-1.6-fine-uploader
Author: Team QWL
Author-email: padova@quag.com
License: MIT
Download-URL: https://github.com/cic79/django-1.6-fine-uploader/archive/0.2.0.1.tar.gz
Keywords: django,fine,uploader
Platform: UNKNOWN
Classifier: Framework :: Django
Classifier: Framework :: Django :: 1.6
Classifier: Intended Audience :: Developers
Classifier: License :: OSI Approved :: BSD License
Classifier: Natural Language :: English
Classifier: Programming Language :: Python :: 2
Classifier: Programming Language :: Python :: 2.7
Classifier: Programming Language :: Python :: 3
Classifier: Programming Language :: Python :: 3.4
Classifier: Programming Language :: Python :: 3.5
Requires-Dist: django (<1.7)
Requires-Dist: six
